{
  "id": "veterinary-jargon",
  "title": "Veterinary Jargon",
  "description": "Explore the specialized language of animal doctors and veterinary science with this fun quiz.",
  "gameCategory": "word-games",
  "questions": [
    {
      "id": "veterinary-jargon-1",
      "question": "What does 'spaying' refer to in veterinary medicine?",
      "options": [
        "Surgically removing the ovaries and usually the uterus of a female animal",
        "Vaccinating an animal",
        "Microchipping a pet",
        "Treating a skin infection"
      ],
      "correctAnswer": 0
    },
    {
      "id": "veterinary-jargon-2",
      "question": "What is 'zoonosis'?",
      "options": [
        "A zoo animal's enclosure",
        "A type of animal behavior",
        "An animal's life span",
        "A disease that can be transmitted from animals to humans"
      ],
      "correctAnswer": 3
    },
    {
      "id": "veterinary-jargon-3",
      "question": "What does 'subcutaneous' mean when giving an injection?",
      "options": [
        "Into the joint",
        "Into the vein",
        "Into the muscle",
        "Under the skin"
      ],
      "correctAnswer": 3
    },
    {
      "id": "veterinary-jargon-4",
      "question": "What is 'palpation' in a veterinary exam?",
      "options": [
        "Taking a blood sample",
        "Listening to the heart",
        "Examining by feeling with the hands to detect abnormalities",
        "Checking the animal's reflexes"
      ],
      "correctAnswer": 2
    },
    {
      "id": "veterinary-jargon-5",
      "question": "What does 'neuter' mean in veterinary terms?",
      "options": [
        "To surgically remove the testicles of a male animal",
        "To declaw",
        "To vaccinate",
        "To deworm"
      ],
      "correctAnswer": 0
    },
    {
      "id": "veterinary-jargon-6",
      "question": "What is 'titer testing'?",
      "options": [
        "A blood test measuring the level of antibodies to determine immunity",
        "A urine analysis",
        "A test for parasites",
        "A test for food allergies"
      ],
      "correctAnswer": 0
    },
    {
      "id": "veterinary-jargon-7",
      "question": "What does 'dysplasia' refer to?",
      "options": [
        "A type of tumor",
        "Abnormal development or formation of a body part, such as hip dysplasia in dogs",
        "A skin condition",
        "A digestive disorder"
      ],
      "correctAnswer": 1
    },
    {
      "id": "veterinary-jargon-8",
      "question": "What is a 'bolus' in veterinary medicine?",
      "options": [
        "An animal carrier",
        "A type of bandage",
        "A surgical instrument",
        "A large pill or a single dose of medication given all at once"
      ],
      "correctAnswer": 3
    },
    {
      "id": "veterinary-jargon-9",
      "question": "What does 'auscultation' mean?",
      "options": [
        "A surgical procedure",
        "Listening to internal body sounds, typically with a stethoscope",
        "Taking the animal's temperature",
        "An eye examination"
      ],
      "correctAnswer": 1
    },
    {
      "id": "veterinary-jargon-10",
      "question": "What is 'parvo' short for?",
      "options": [
        "Parasite vomiting",
        "Parasitic organism",
        "Parvovirus, a highly contagious viral illness in dogs",
        "Partial vaccination"
      ],
      "correctAnswer": 2
    },
    {
      "id": "veterinary-jargon-11",
      "question": "What does 'prophylactic' mean in veterinary care?",
      "options": [
        "A type of surgery",
        "An emergency procedure",
        "A preventive treatment or measure to guard against disease",
        "A diagnostic test"
      ],
      "correctAnswer": 2
    },
    {
      "id": "veterinary-jargon-12",
      "question": "What is 'deworming'?",
      "options": [
        "Removing ticks from an animal",
        "Cleaning an animal's ears",
        "Treating an animal with medication to eliminate internal parasitic worms",
        "Treating a skin fungus"
      ],
      "correctAnswer": 2
    },
    {
      "id": "veterinary-jargon-13",
      "question": "What does 'presenting complaint' mean in a vet visit?",
      "options": [
        "A formal complaint about the vet",
        "A billing dispute",
        "The reason or symptoms that prompted the owner to bring the animal in for examination",
        "A follow-up appointment"
      ],
      "correctAnswer": 2
    },
    {
      "id": "veterinary-jargon-14",
      "question": "What is 'euthanasia' in veterinary context?",
      "options": [
        "A type of anesthesia",
        "A vaccination schedule",
        "A sedation technique",
        "The humane, painless ending of an animal's life to relieve suffering"
      ],
      "correctAnswer": 3
    },
    {
      "id": "veterinary-jargon-15",
      "question": "What does 'FeLV' stand for in feline medicine?",
      "options": [
        "Feline Lower Extremity Vaccination",
        "Feline Ear and Lung Virus",
        "Feline Liver Vaccine",
        "Feline Leukemia Virus"
      ],
      "correctAnswer": 3
    }
  ]
}
