{
  "id": "elephants-gentle-giants-quiz",
  "title": "Elephants: Gentle Giants",
  "description": "Learn about the world's largest land animals, their intelligence, social bonds, and conservation.",
  "gameCategory": "general-knowledge",
  "questions": [
    {
      "id": "elephants-gentle-giants-quiz-1",
      "question": "How many species of elephants are currently recognized?",
      "options": [
        "2",
        "3",
        "4",
        "1"
      ],
      "correctAnswer": 1
    },
    {
      "id": "elephants-gentle-giants-quiz-2",
      "question": "Which elephant species is the largest land animal on Earth?",
      "options": [
        "African forest elephant",
        "African bush elephant",
        "They are all the same size",
        "Asian elephant"
      ],
      "correctAnswer": 1
    },
    {
      "id": "elephants-gentle-giants-quiz-3",
      "question": "An elephant's trunk contains approximately how many muscles?",
      "options": [
        "40,000",
        "100,000",
        "10,000",
        "1,000"
      ],
      "correctAnswer": 0
    },
    {
      "id": "elephants-gentle-giants-quiz-4",
      "question": "Elephants are known to mourn their dead. What do they do when they encounter the bones of a deceased elephant?",
      "options": [
        "Trumpet loudly and run away",
        "Gently touch and examine them with their trunks",
        "Ignore them",
        "Bury them"
      ],
      "correctAnswer": 1
    },
    {
      "id": "elephants-gentle-giants-quiz-5",
      "question": "How long is the gestation period of an elephant, the longest of any land animal?",
      "options": [
        "22 months",
        "28 months",
        "12 months",
        "16 months"
      ],
      "correctAnswer": 0
    },
    {
      "id": "elephants-gentle-giants-quiz-6",
      "question": "African elephants can be distinguished from Asian elephants by what feature?",
      "options": [
        "African elephants have much larger ears",
        "African elephants have shorter tusks",
        "African elephants have more hair",
        "African elephants are smaller"
      ],
      "correctAnswer": 0
    },
    {
      "id": "elephants-gentle-giants-quiz-7",
      "question": "Elephant herds are typically led by whom?",
      "options": [
        "The largest male",
        "The oldest female (matriarch)",
        "The youngest adult",
        "They have no leader"
      ],
      "correctAnswer": 1
    },
    {
      "id": "elephants-gentle-giants-quiz-8",
      "question": "How much food does an adult elephant eat per day?",
      "options": [
        "50 pounds",
        "150 pounds",
        "300 pounds",
        "500 pounds"
      ],
      "correctAnswer": 2
    },
    {
      "id": "elephants-gentle-giants-quiz-9",
      "question": "Elephants communicate using low-frequency sounds called infrasound. How far can these travel?",
      "options": [
        "10 miles",
        "1 mile",
        "6 miles",
        "3 miles"
      ],
      "correctAnswer": 2
    },
    {
      "id": "elephants-gentle-giants-quiz-10",
      "question": "Which elephant is known for being used historically in Asian warfare and ceremonies?",
      "options": [
        "African forest elephant",
        "Woolly mammoth",
        "African bush elephant",
        "Asian elephant"
      ],
      "correctAnswer": 3
    },
    {
      "id": "elephants-gentle-giants-quiz-11",
      "question": "Elephants are one of the few animals that can recognize themselves in a mirror. What does this indicate?",
      "options": [
        "Good eyesight",
        "Fear response",
        "Territorial behavior",
        "Self-awareness"
      ],
      "correctAnswer": 3
    },
    {
      "id": "elephants-gentle-giants-quiz-12",
      "question": "What do elephants use their tusks for?",
      "options": [
        "Digging, stripping bark, and defense",
        "Eating tough vegetation",
        "Decoration only",
        "Only fighting"
      ],
      "correctAnswer": 0
    },
    {
      "id": "elephants-gentle-giants-quiz-13",
      "question": "How much water can an elephant's trunk hold at one time?",
      "options": [
        "2 gallons",
        "8 gallons",
        "4 gallons",
        "1 gallon"
      ],
      "correctAnswer": 0
    },
    {
      "id": "elephants-gentle-giants-quiz-14",
      "question": "The ivory trade has been a major threat to elephants. When was the international ivory trade ban enacted?",
      "options": [
        "1975",
        "1989",
        "1995",
        "1982"
      ],
      "correctAnswer": 1
    },
    {
      "id": "elephants-gentle-giants-quiz-15",
      "question": "Elephants are known to be afraid of which small insects?",
      "options": [
        "Butterflies",
        "Ants",
        "Mosquitoes",
        "Bees"
      ],
      "correctAnswer": 3
    }
  ]
}
